smartconfigparser/__init__.py
SmartConfigParser-1.0.0.dist-info/LICENSE
SmartConfigParser-1.0.0.dist-info/METADATA
SmartConfigParser-1.0.0.dist-info/WHEEL
SmartConfigParser-1.0.0.dist-info/top_level.txt
SmartConfigParser-1.0.0.dist-info/zip-safe
SmartConfigParser-1.0.0.dist-info/RECORD
