Metadata-Version: 2.1
Name: SmartConfigParser
Version: 1.0.0
Summary: Simplifies and enchances functionalities in Python's ConfigParser
Home-page: http://github.com/ricard33/smartconfigparser
Author: Cédric RICARD
Author-email: ricard33@gmail.com
License: MIT License
Keywords: ConfiParser,ini
Platform: any
Classifier: Development Status :: 5 - Production/Stable
Classifier: Intended Audience :: Developers
Classifier: Topic :: Utilities
Classifier: License :: OSI Approved :: MIT License
Classifier: Programming Language :: Python
Classifier: Programming Language :: Python :: 2.7
Classifier: Programming Language :: Python :: 3.4
Classifier: Programming Language :: Python :: 3.5
Classifier: Programming Language :: Python :: 3.6
Classifier: Programming Language :: Python :: 3.7
